{
  "model": "Random Forest Regressor",
  "train_period": [
    "2020-01-01",
    "2025-12-31"
  ],
  "test_period": [
    "2026-01-01",
    "2026-05-26 17:00:00"
  ],
  "rows": {
    "total": 56094,
    "train": 52596,
    "test": 3498
  },
  "grid_search_rows": 52596,
  "best_params": {
    "model__max_depth": 10,
    "model__min_samples_leaf": 4,
    "model__n_estimators": 180
  },
  "best_cv_neg_mae": -1.483989110987379,
  "regression": {
    "mae": 0.8518144345611889,
    "rmse": 2.600885298752757,
    "r2": 0.2898374303543574
  },
  "rain_alert": {
    "accuracy": 0.8853630646083476,
    "f1": 0.6191832858499525,
    "confusion_matrix": [
      [
        2771,
        268
      ],
      [
        133,
        326
      ]
    ],
    "classification_report": {
      "0": {
        "precision": 0.9542011019283747,
        "recall": 0.9118130964132939,
        "f1-score": 0.9325256604408548,
        "support": 3039.0
      },
      "1": {
        "precision": 0.5488215488215489,
        "recall": 0.710239651416122,
        "f1-score": 0.6191832858499525,
        "support": 459.0
      },
      "accuracy": 0.8853630646083476,
      "macro avg": {
        "precision": 0.7515113253749618,
        "recall": 0.8110263739147079,
        "f1-score": 0.7758544731454037,
        "support": 3498.0
      },
      "weighted avg": {
        "precision": 0.9010080730901721,
        "recall": 0.8853630646083476,
        "f1-score": 0.8914095512535409,
        "support": 3498.0
      }
    }
  }
}